claims_lib/__init__.py
claims_lib/claims_due_count.py
claims_lib/due_date.py
claims_lib/email_report.py
claims_lib/submission_date.py
claims_lib/uniq_claim_id.py
claims_lib-0.1.1.dist-info/LICENSE
claims_lib-0.1.1.dist-info/METADATA
claims_lib-0.1.1.dist-info/WHEEL
claims_lib-0.1.1.dist-info/top_level.txt
claims_lib-0.1.1.dist-info/RECORD
